CCF_translator/PointSet.py
CCF_translator/Volume.py
CCF_translator/VolumeSeries.py
CCF_translator/__init__.py
CCF_translator/read_write.py
CCF_translator/deformation/__init__.py
CCF_translator/deformation/apply_deformation.py
CCF_translator/deformation/forward_transform.py
CCF_translator/deformation/route_calculation.py
CCF_translator/deformation/interpolation/NearestNDInterpolator.py
CCF_translator/deformation/interpolation/__init__.py
CCF_translator/metadata/translation_metadata.csv
CCF_translator-0.22.dist-info/LICENSE
CCF_translator-0.22.dist-info/METADATA
CCF_translator-0.22.dist-info/WHEEL
CCF_translator-0.22.dist-info/top_level.txt
CCF_translator-0.22.dist-info/RECORD
