Metadata-Version: 2.1
Name: CCF_translator
Version: 0.22
Summary: a package to translate data between common coordinate templates
Home-page: https://github.com/Neural-Systems-at-UIO/CCF_translator
Author-email: harry.carey@medisin.uio.no
License: MIT
Keywords: neuroinformatics,brain,atlas,brainglobe,neuroscience
Classifier: Development Status :: 5 - Production/Stable
Classifier: Intended Audience :: Science/Research
Classifier: Topic :: Scientific/Engineering :: Bio-Informatics
Classifier: License :: OSI Approved :: MIT License
Classifier: Programming Language :: Python
License-File: LICENSE
Requires-Dist: numpy
Requires-Dist: nibabel
Requires-Dist: scipy
Requires-Dist: networkx
Requires-Dist: pandas
Requires-Dist: requests
